setup.py
nose_docker/__init__.py
nose_docker/config.py
nose_docker/plugin.py
nose_docker/version.py
nose_docker.egg-info/PKG-INFO
nose_docker.egg-info/SOURCES.txt
nose_docker.egg-info/dependency_links.txt
nose_docker.egg-info/entry_points.txt
nose_docker.egg-info/requires.txt
nose_docker.egg-info/top_level.txt
tests/__init__.py
tests/base.py
tests/test_version.py