Metadata-Version: 1.1
Name: nose-docker
Version: 0.1.0
Summary: nose-docker allows you to run tests inside docker containers.
Home-page: https://github.com/heynemann/nose-docker
Author: Bernardo Heynemann
Author-email: heynemann@gmail.com
License: MIT
Platform: UNKNOWN
Classifier: Development Status :: 4 - Beta
Classifier: Intended Audience :: Developers
Classifier: License :: OSI Approved :: MIT License
Classifier: Natural Language :: English
Classifier: Operating System :: Unix
Classifier: Programming Language :: Python :: 2.7
Classifier: Programming Language :: Python :: 3.4
Classifier: Programming Language :: Python :: Implementation :: PyPy
Classifier: Operating System :: OS Independent
